volkit/__init__.py
volkit/arb/__init__.py
volkit/datasets/__init__.py
volkit/datasets/data/spxw.csv
volkit/datasets/data/spxw20190626.csv
volkit/datasets/loader_spxw.py
volkit/estimate/__init__.py
volkit/estimate/future_from_option_prices.py
volkit/estimate/future_from_option_prices_plot.py
volkit/estimate/future_from_option_quotes.py
volkit/estimate/future_from_option_quotes_plot.py
volkit/estimate/future_res.py
volkit/estimate/vol_from_option_prices.py
volkit/pricing/__init__.py
volkit/pricing/future.py
volkit/utils/__init__.py
volkit-0.2.1.dist-info/LICENSE
volkit-0.2.1.dist-info/METADATA
volkit-0.2.1.dist-info/WHEEL
volkit-0.2.1.dist-info/RECORD
